cait_sith_py-0.2.6.dist-info/METADATA
cait_sith_py-0.2.6.dist-info/WHEEL
cait_sith_py-0.2.6.dist-info/license_files/LICENSE
cait_sith/__init__.py
cait_sith/cait_sith.pyd
cait_sith_py-0.2.6.dist-info/RECORD
