Metadata-Version: 2.3
Name: cait_sith_py
Version: 0.2.6
Classifier: Programming Language :: Rust
Classifier: Programming Language :: Python :: Implementation :: CPython
Classifier: Programming Language :: Python :: Implementation :: PyPy
License-File: LICENSE
Summary: Cait Sith rust wrapper on python
Requires-Python: >=3.7
Project-URL: repository, https://github.com/here-wallet/cait-sith-py
